CHANGES.txt
CONTRIBUTORS.txt
MANIFEST.in
README.txt
setup.cfg
setup.py
collective/__init__.py
collective.salesforce.query.egg-info/PKG-INFO
collective.salesforce.query.egg-info/SOURCES.txt
collective.salesforce.query.egg-info/dependency_links.txt
collective.salesforce.query.egg-info/entry_points.txt
collective.salesforce.query.egg-info/namespace_packages.txt
collective.salesforce.query.egg-info/not-zip-safe
collective.salesforce.query.egg-info/paster_plugins.txt
collective.salesforce.query.egg-info/requires.txt
collective.salesforce.query.egg-info/top_level.txt
collective/salesforce/__init__.py
collective/salesforce/query/__init__.py
collective/salesforce/query/config.py
collective/salesforce/query/setuphandlers.py
collective/salesforce/query/sfq_catalog_tool.py
collective/salesforce/query/vocabularies.py
collective/salesforce/query/widgets.py
collective/salesforce/query/browser/__init__.py
collective/salesforce/query/browser/salesforcequeryview.py
collective/salesforce/query/content/__init__.py
collective/salesforce/query/content/salesforcegenericobject.py
collective/salesforce/query/content/salesforcequery.py
collective/salesforce/query/interfaces/__init__.py
collective/salesforce/query/interfaces/salesforcegenericobject.py
collective/salesforce/query/interfaces/salesforcequery.py
collective/salesforce/query/portlets/__init__.py
collective/salesforce/query/tests/__init__.py
collective/salesforce/query/tests/base.py
collective/salesforce/query/tests/test_doctest.py
collective/salesforce/query/tests/test_salesforcequery.py
docs/HISTORY.txt
docs/INSTALL.txt
docs/LICENSE.txt