Metadata-Version: 1.0
Name: collective.salesforce.query
Version: 2.0.1
Summary: UNKNOWN
Home-page: http://svn.plone.org/svn/plone/plone.example
Author: Franco Pellegrini
Author-email: frapell@menttes.com
License: GPL
Platform: UNKNOWN
Classifier: Framework :: Plone
Classifier: Intended Audience :: Developers
Classifier: Topic :: Software Development :: Libraries :: Python Modules
Classifier: License :: OSI Approved :: GNU General Public License (GPL)
